fenharel_command_center/__init__.py
fenharel_command_center/command.py
fenharel_command_center/command_center.py
fenharel_command_center/input_utils.py
fenharel_command_center-0.0.3.dist-info/METADATA
fenharel_command_center-0.0.3.dist-info/WHEEL
fenharel_command_center-0.0.3.dist-info/licenses/LICENSE
fenharel_command_center-0.0.3.dist-info/RECORD
